README.rst
setup.py
docker_tag_naming/__init__.py
docker_tag_naming/bump.py
docker_tag_naming/constants.py
docker_tag_naming/forge.py
docker_tag_naming/latest.py
docker_tag_naming/main.py
docker_tag_naming/refresh.py
docker_tag_naming/utils.py
docker_tag_naming.egg-info/PKG-INFO
docker_tag_naming.egg-info/SOURCES.txt
docker_tag_naming.egg-info/dependency_links.txt
docker_tag_naming.egg-info/entry_points.txt
docker_tag_naming.egg-info/requires.txt
docker_tag_naming.egg-info/top_level.txt
docker_tag_naming/tests/__init__.py
docker_tag_naming/tests/test_basic.py