Metadata-Version: 1.1
Name: docker-tag-naming
Version: 1.0.4
Summary: Name and query docker tags
Home-page: https://github.com/andresriancho/docker-tag-naming/
Author: Andres Riancho
Author-email: andres.riancho@gmail.com
License: GNU General Public License v2 (GPLv2)
Platform: Linux
Classifier: Development Status :: 5 - Production/Stable
Classifier: Intended Audience :: Developers
Classifier: License :: OSI Approved :: GNU General Public License v2 (GPLv2)
Classifier: Natural Language :: English
Classifier: Operating System :: POSIX :: Linux
Classifier: Programming Language :: Python
Classifier: Programming Language :: Python :: 2.7
Classifier: Topic :: System :: Monitoring
